snakemake_executor_plugin_kubernetes/__init__.py
snakemake_executor_plugin_kubernetes-0.5.1.dist-info/LICENSE
snakemake_executor_plugin_kubernetes-0.5.1.dist-info/METADATA
snakemake_executor_plugin_kubernetes-0.5.1.dist-info/WHEEL
snakemake_executor_plugin_kubernetes-0.5.1.dist-info/RECORD
